tsfresh/__init__.py
tsfresh/defaults.py
tsfresh/convenience/__init__.py
tsfresh/convenience/bindings.py
tsfresh/convenience/relevant_extraction.py
tsfresh/examples/__init__.py
tsfresh/examples/driftbif_simulation.py
tsfresh/examples/har_dataset.py
tsfresh/examples/robot_execution_failures.py
tsfresh/feature_extraction/__init__.py
tsfresh/feature_extraction/data.py
tsfresh/feature_extraction/extraction.py
tsfresh/feature_extraction/feature_calculators.py
tsfresh/feature_extraction/settings.py
tsfresh/feature_selection/__init__.py
tsfresh/feature_selection/relevance.py
tsfresh/feature_selection/selection.py
tsfresh/feature_selection/significance_tests.py
tsfresh/scripts/__init__.py
tsfresh/scripts/measure_execution_time.py
tsfresh/scripts/run_tsfresh.py
tsfresh/scripts/test_timing.py
tsfresh/transformers/__init__.py
tsfresh/transformers/feature_augmenter.py
tsfresh/transformers/feature_selector.py
tsfresh/transformers/per_column_imputer.py
tsfresh/transformers/relevant_feature_augmenter.py
tsfresh/utilities/__init__.py
tsfresh/utilities/dataframe_functions.py
tsfresh/utilities/distribution.py
tsfresh/utilities/profiling.py
tsfresh/utilities/string_manipulation.py
peritus_test_tsfresh-1.1.0.dist-info/AUTHORS.rst
peritus_test_tsfresh-1.1.0.dist-info/LICENSE.txt
peritus_test_tsfresh-1.1.0.dist-info/METADATA
peritus_test_tsfresh-1.1.0.dist-info/WHEEL
peritus_test_tsfresh-1.1.0.dist-info/top_level.txt
peritus_test_tsfresh-1.1.0.dist-info/RECORD
